AUTHORS.rst
CONTRIBUTING.rst
HISTORY.rst
LICENSE
MANIFEST.in
README.rst
setup.cfg
setup.py
docs/Makefile
docs/authors.rst
docs/conf.py
docs/contributing.rst
docs/history.rst
docs/index.rst
docs/installation.rst
docs/make.bat
docs/readme.rst
docs/usage.rst
pysarpu/__init__.py
pysarpu/classification.py
pysarpu/cli.py
pysarpu/likelihood_models.py
pysarpu/propensity.py
pysarpu/pysarpu.py
pysarpu.egg-info/PKG-INFO
pysarpu.egg-info/SOURCES.txt
pysarpu.egg-info/dependency_links.txt
pysarpu.egg-info/entry_points.txt
pysarpu.egg-info/not-zip-safe
pysarpu.egg-info/requires.txt
pysarpu.egg-info/top_level.txt
tests/__init__.py
tests/test_pysarpu.py