Metadata-Version: 2.1
Name: pysarpu
Version: 0.1.0
Summary: PU learning under SAR assumption with unknown propensity. Implementation of the general SAR-EM algorithm.
Home-page: https://github.com/ocoudray/pysarpu
Author: Olivier COUDRAY
Author-email: olivier.coudray.15@polytechnique.org
License: MIT license
Keywords: pysarpu
Classifier: Development Status :: 2 - Pre-Alpha
Classifier: Intended Audience :: Developers
Classifier: License :: OSI Approved :: MIT License
Classifier: Natural Language :: English
Classifier: Programming Language :: Python :: 3
Classifier: Programming Language :: Python :: 3.6
Classifier: Programming Language :: Python :: 3.7
Classifier: Programming Language :: Python :: 3.8
Requires-Python: >=3.6
License-File: LICENSE
License-File: AUTHORS.rst
